spsspro_custom_script/__init__.py
spsspro_custom_script/custom_script.py
spsspro_custom_script/custom_script_extra.py
spsspro_custom_script/errors.py
spsspro_custom_script/script_executor.py
spsspro_custom_script/spsspro_pickle.py
spsspro_custom_script/value_objects.py
spsspro_custom_script-2025.11.11.dist-info/METADATA
spsspro_custom_script-2025.11.11.dist-info/WHEEL
spsspro_custom_script-2025.11.11.dist-info/top_level.txt
spsspro_custom_script-2025.11.11.dist-info/RECORD
