Metadata-Version: 2.4
Name: spsspro_custom_script
Version: 2025.11.11
Summary: spsspro sdk
Author: spsspro
Requires-Python: >=3.8
Requires-Dist: pandas==1.4.1
Requires-Dist: numpy==1.22.2
Requires-Dist: openpyxl==3.1.2
Requires-Dist: pydantic==1.8.2
Requires-Dist: matplotlib==3.4.3
Requires-Dist: cloudpickle~=3.0.0
Requires-Dist: rdkit~=2024.3.2
Requires-Dist: RestrictedPython==6.0
Dynamic: author
Dynamic: requires-dist
Dynamic: requires-python
Dynamic: summary
